ALU/ALU_Behavioural.v
// Code your design here
//Verilog module for an ALU
module ALU(
    A,
    B,
    Op,
    R   );
    
    //inputs,outputs and internal variables declared here
    input [7:0] A,B;
    input [2:0] Op;
    output [7:0] R;
    wire [7:0] Reg1,Reg2;
    reg [7:0] Reg3;
    
    //Assign A and B to internal variables for doing operations
    assign Reg1 = A;
    assign Reg2 = B;
    //Assign the output 
    assign R = Reg3;

    //Always block with inputs in the sensitivity list.
    always @(Op or Reg1 or Reg2)
    begin
        case (Op)
            0 : Reg3 = Reg1 + Reg2;  //addition
         1 : Reg3 = Reg1 - Reg2; //subtraction
         2 : Reg3 = ~Reg1;  //NOT gate
         3 : Reg3 = ~(Reg1 & Reg2); //NAND gate 
         4 : Reg3 = ~(Reg1 | Reg2); //NOR gate               
         5 : Reg3 = Reg1 & Reg2;  //AND gate
         6 : Reg3 = Reg1 | Reg2;  //OR gate    
         7 : Reg3 = Reg1 ^ Reg2; //XOR gate  
        endcase 
    end
    
endmodule

ALU_Behavioural_tb.v
// Code your testbench here
// or browse Examples
module tb_alu;

    // Inputs
    reg [7:0] A;
    reg [7:0] B;
    reg [2:0] Op;

    // Outputs
    wire [7:0] R;

    // Instantiate the Unit Under Test (UUT)
    ALU uut ( 
        .A(A), 
        .B(B), 
        .Op(Op), 
        .R(R)
    );
    
    initial begin
        // Apply inputs.
        A = 8'b01101010;
        B = 8'b00111011;
        Op = 0; #100;
        Op = 1; #100;
        Op = 2; #100;
        Op = 3; #100;
        Op = 4; #100;
        Op = 5; #100;
        Op = 6; #100;
        Op = 7; #100;
    end
      
endmodule

ALU/ALU_B1.vcd
$date
	Sun Jul 21 14:47:52 2024
$end
$version
	Icarus Verilog
$end
$timescale
	1s
$end
$scope module tb_alu $end
$var wire 8 ! R [7:0] $end
$upscope $end
$enddefinitions $end
#0
$dumpvars
b10100101 !
$end
#100
b101111 !
#200
b10010101 !
#300
b11010101 !
#400
b10000100 !
#500
b101010 !
#600
b1111011 !
#700
b1010001 !
